paramorator.py
paramorator-1.0.2.dist-info/LICENSE
paramorator-1.0.2.dist-info/WHEEL
paramorator-1.0.2.dist-info/METADATA
paramorator-1.0.2.dist-info/RECORD
