Metadata-Version: 2.1
Name: paramorator
Version: 1.0.2
Summary: A dead simple utility for defining decorators with parameters that make type checkers happy.
Author-email: Ryan Morshead <ryan.morshead@gmail.com>
Classifier: License :: OSI Approved :: MIT License
Project-URL: Home, https://pypi.org/project/paramorator
